INSTALL.rst
MANIFEST.in
Makefile
NEWS.rst
README.rst
setup.cfg
setup.py
scripts/oracreate.py
scripts/oradelete.py
scripts/oradiff.py
scripts/oradrop.py
scripts/orafind.py
scripts/oragrant.py
scripts/oramerge.py
src/ll/__init__.py
src/ll/orasql/__init__.py
src/ll/orasql/scripts/__init__.py
src/ll/orasql/scripts/oracreate.py
src/ll/orasql/scripts/oradelete.py
src/ll/orasql/scripts/oradiff.py
src/ll/orasql/scripts/oradrop.py
src/ll/orasql/scripts/orafind.py
src/ll/orasql/scripts/oragrant.py
src/ll/orasql/scripts/oramerge.py
src/ll_orasql.egg-info/PKG-INFO
src/ll_orasql.egg-info/SOURCES.txt
src/ll_orasql.egg-info/dependency_links.txt
src/ll_orasql.egg-info/entry_points.txt
src/ll_orasql.egg-info/namespace_packages.txt
src/ll_orasql.egg-info/not-zip-safe
src/ll_orasql.egg-info/requires.txt
src/ll_orasql.egg-info/top_level.txt
test/test_orasql.py