Metadata-Version: 1.0
Name: ll-orasql
Version: 1.27
Summary: Utilities for working with cx_Oracle
Home-page: http://www.livinglogic.de/Python/orasql/
Author: Walter Doerwald
Author-email: walter@livinglogic.de
License: Python
Download-URL: http://www.livinglogic.de/Python/Download.html#orasql
Keywords: database,Oracle,cx_Oracle,record,procedure,schema
Platform: UNKNOWN
Classifier: Development Status :: 4 - Beta
Classifier: Intended Audience :: Developers
Classifier: License :: OSI Approved :: Python License (CNRI Python License)
Classifier: Operating System :: OS Independent
Classifier: Programming Language :: Python
Classifier: Topic :: Database
